yaclog_ksp/__init__.py
yaclog_ksp/__main__.py
yaclog_ksp/cfgnode.py
yaclog_ksp/script.py
yaclog_ksp-1.3.1.dist-info/licenses/LICENSE.md
yaclog_ksp-1.3.1.dist-info/METADATA
yaclog_ksp-1.3.1.dist-info/WHEEL
yaclog_ksp-1.3.1.dist-info/entry_points.txt
yaclog_ksp-1.3.1.dist-info/top_level.txt
yaclog_ksp-1.3.1.dist-info/RECORD
