Metadata-Version: 2.4
Name: yaclog-ksp
Version: 1.3.1
Summary: Kerbal Space Program changelog file generator
Author-email: Andrew Cassidy <drewcassidy@me.com>
License-Expression: AGPL-3.0-or-later
Project-URL: Source, https://git.offworldcolonies.nexus/drewcassidy/yaclog-ksp
Project-URL: Changelog, https://git.offworldcolonies.nexus/drewcassidy/yaclog-ksp/src/branch/main/CHANGELOG.md
Project-URL: Forum Post, https://forum.kerbalspaceprogram.com/index.php?/topic/201784-*
Keywords: changelog,commandline,markdown,KSP
Classifier: Development Status :: 5 - Production/Stable
Classifier: Intended Audience :: Developers
Classifier: Operating System :: OS Independent
Classifier: Programming Language :: Python :: 3 :: Only
Classifier: Programming Language :: Python :: 3
Classifier: Topic :: Text Processing :: Markup :: Markdown
Classifier: Topic :: Software Development :: Version Control :: Git
Classifier: Topic :: Utilities
Classifier: Topic :: Games/Entertainment :: Simulation
Requires-Python: >=3.10
License-File: LICENSE.md
Requires-Dist: Click>=8.0
Requires-Dist: yaclog>=1.6
Dynamic: license-file
